trml/__init__.py
trml/color.py
trml/lexer.py
pyTRML-0.0.0.dist-info/METADATA
pyTRML-0.0.0.dist-info/WHEEL
pyTRML-0.0.0.dist-info/top_level.txt
pyTRML-0.0.0.dist-info/RECORD
