Metadata-Version: 2.1
Name: pyTRML
Version: 0.0.0
Summary: Terminal Rendering Markup Language
Home-page: UNKNOWN
Author: GrandMoff100
Author-email: nlarsen23.student@gmail.com
License: UNKNOWN
Platform: UNKNOWN
Requires-Dist: colorama
